flask_sqlalchemy_magic_query/__init__.py
flask_sqlalchemy_magic_query/flask_sqlalchemy_magic_query.py
flask_sqlalchemy_magic_query-0.1.3.3.dist-info/LICENSE
flask_sqlalchemy_magic_query-0.1.3.3.dist-info/METADATA
flask_sqlalchemy_magic_query-0.1.3.3.dist-info/WHEEL
flask_sqlalchemy_magic_query-0.1.3.3.dist-info/top_level.txt
flask_sqlalchemy_magic_query-0.1.3.3.dist-info/RECORD
