Metadata-Version: 2.1
Name: flask-sqlalchemy-magic-query
Version: 0.1.3.3
Summary: Converts HTTP URL query string parameters to flask_sqlalchemy query results
Home-page: https://github.com/gabrielligoski/flask_sqlalchemy_magic_query
Author: Gabriel Ligoski
Author-email: gabriel.ligoski@gmail.com
License: MIT
License-File: LICENSE
Requires-Dist: flask
Requires-Dist: sqlalchemy
Requires-Dist: flask-sqlalchemy
